hidjango/__init__.py
hidjango/main.py
tests/__init__.py
tests/test_main.py
hidjango-1.1.0.dist-info/LICENSE
hidjango-1.1.0.dist-info/METADATA
hidjango-1.1.0.dist-info/WHEEL
hidjango-1.1.0.dist-info/entry_points.txt
hidjango-1.1.0.dist-info/top_level.txt
hidjango-1.1.0.dist-info/RECORD
