Metadata-Version: 2.1
Name: hidjango
Version: 1.1.0
Summary: A library to simplify Django project initialization
Home-page: https://github.com/parsarezaee/HiDjango
Author: Parsa Rezaei
Author-email: rezaei.7parsa@gmail.com
License: MIT
Keywords: django library project automation devops
Platform: UNKNOWN
Requires-Python: >=3.7
License-File: LICENSE
Requires-Dist: django (>=3.2)
Requires-Dist: pytest (>=7.0.0)
Requires-Dist: python-dotenv
Requires-Dist: textwrap3 (>=0.9.2)
